CHANGES.txt
MANIFEST.in
README.txt
setup.py
src/ao/__init__.py
src/ao.tron.egg-info/PKG-INFO
src/ao.tron.egg-info/SOURCES.txt
src/ao.tron.egg-info/dependency_links.txt
src/ao.tron.egg-info/requires.txt
src/ao.tron.egg-info/top_level.txt
src/ao.tron.egg-info/zip-safe
src/ao/tron/__init__.py
src/ao/tron/board.txt
src/ao/tron/input.txt
src/ao/tron/tests.py